sequential/pc.v
module PC(
    input clk,
    input reset,
    input [63:0] pc_in,
    output reg [63:0] pc_out
);
    always @(posedge clk or posedge reset) begin
        if(reset)
            pc_out <= 64'd0; 
        else
            pc_out <= pc_in; 
    end
endmodule

module PC_adder(
    input [63:0] pc,
    output [63:0] pc_4
);
    assign pc_4 = pc + 64'd4; 
endmodule

module PC_branchadder(
    input [63:0] pc_curr,
    input [63:0] imm,
    output [63:0] branch_target
);
    assign branch_target = pc_curr + imm; 
endmodule

module next_pc_mux(
    input Branch,
    input Zero,
    input [63:0] pc_plus4,
    input [63:0] branch_target,
    output reg [63:0] next_pc
);
    always @(*) begin
       
        if (Branch && Zero)
            next_pc = branch_target;
        else
            next_pc = pc_plus4;
    end
endmodule

sequential/instruction_fetch.v
`define IMEM_SIZE 4096

module Instruction_Fetch_Stage(
    input clk,
    input reset,
    input Branch,         
    input Zero,             
    input [63:0] imm,       
    output [31:0] instr,    
    output [63:0] pc_out   
);

    wire [63:0] pc_next_wire;
    wire [63:0] pc_plus4;
    wire [63:0] branch_target;

    PC program_counter (
        .clk(clk),
        .reset(reset),
        .pc_in(pc_next_wire),
        .pc_out(pc_out)
    );

    Instruction_Memory imem (
        .addr(pc_out),
        .instr(instr)
    );

    PC_adder add4 (
        .pc(pc_out),
        .pc_4(pc_plus4)
    );

    PC_branchadder add_branch (
        .pc_curr(pc_out),
        .imm(imm),
        .branch_target(branch_target)
    );

    next_pc_mux mux (
        .Branch(Branch),
        .Zero(Zero),
        .pc_plus4(pc_plus4),
        .branch_target(branch_target),
        .next_pc(pc_next_wire)
    );

endmodule

module Instruction_Memory(
    input [63:0] addr,
    output [31:0] instr
);
    reg [7:0] mem [0:`IMEM_SIZE-1];

    initial begin
        $readmemh("instructions.txt", mem); 
    end

    assign instr = {mem[addr], mem[addr+1], mem[addr+2], mem[addr+3]};
endmodule

sequential/if_stage_tb.v
`timescale 1ns / 1ps

module if_stage_tb;
    // Testbench Signals
    reg clk;
    reg reset;
    reg Branch;
    reg Zero;
    reg [63:0] imm;
    
    wire [31:0] instr;
    wire [63:0] pc_out;

    // Instantiate the Fetch Stage Wrapper
    Instruction_Fetch_Stage uut (
        .clk(clk),
        .reset(reset),
        .Branch(Branch),
        .Zero(Zero),
        .imm(imm),
        .instr(instr),
        .pc_out(pc_out)
    );

    // Clock generation: 10ns period (100MHz)
    always #5 clk = ~clk;

    initial begin

        $dumpfile("if_stage.vcd");
        $dumpvars(0, if_stage_tb);
        
        // --- Initialization ---
        clk = 0;
        reset = 1;
        Branch = 0;
        Zero = 0;
        imm = 64'd0;

        // Reset the system
        #15 reset = 0;
        $display("Time\t PC_Out\t\t Instruction");
        $display("------------------------------------------");

        // --- Test 1: Sequential Execution (PC + 4) ---
        // Let it run for 3 cycles to see PC go 0 -> 4 -> 8
        repeat (3) @(posedge clk);
        $display("%t\t %h\t %h", $time, pc_out, instr);

        // --- Test 2: Successful Branch (PC + Imm) ---
        // Simulate a BEQ where registers are equal (Zero=1)
        // Let's say we want to jump 16 bytes forward
        imm = 64'd16; 
        Branch = 1;
        Zero = 1;
        
        @(posedge clk);
        #1; // Wait for logic to settle
        $display("%t\t %h\t %h (Branched!)", $time, pc_out, instr);

        // --- Test 3: Failed Branch (Stay at PC + 4) ---
        // Branch is 1 but Zero is 0 (Condition not met)
        Branch = 1;
        Zero = 0;
        
        @(posedge clk);
        #1;
        $display("%t\t %h\t %h (Branch Failed - Sequential)", $time, pc_out, instr);

        #20;
        $finish;
    end

    // Monitor for debugging
    initial begin
        $monitor("Cycle: PC=%h, Instr=%h, Branch=%b, Zero=%b", pc_out, instr, Branch, Zero);
    end

endmodule

sequential/if_stage.vcd
$date
	Sun Feb 22 18:52:10 2026
$end
$version
	Icarus Verilog
$end
$timescale
	1ps
$end
$scope module if_stage_tb $end
$var wire 64 ! pc_out [63:0] $end
$var wire 32 " instr [31:0] $end
$var reg 1 # Branch $end
$var reg 1 $ Zero $end
$var reg 1 % clk $end
$var reg 64 & imm [63:0] $end
$var reg 1 ' reset $end
$scope module uut $end
$var wire 1 # Branch $end
$var wire 1 $ Zero $end
$var wire 1 % clk $end
$var wire 64 ( imm [63:0] $end
$var wire 1 ' reset $end
$var wire 64 ) pc_plus4 [63:0] $end
$var wire 64 * pc_out [63:0] $end
$var wire 64 + pc_next_wire [63:0] $end
$var wire 32 , instr [31:0] $end
$var wire 64 - branch_target [63:0] $end
$scope module add4 $end
$var wire 64 . pc_4 [63:0] $end
$var wire 64 / pc [63:0] $end
$upscope $end
$scope module add_branch $end
$var wire 64 0 imm [63:0] $end
$var wire 64 1 pc_curr [63:0] $end
$var wire 64 2 branch_target [63:0] $end
$upscope $end
$scope module imem $end
$var wire 32 3 instr [31:0] $end
$var wire 64 4 addr [63:0] $end
$upscope $end
$scope module mux $end
$var wire 1 # Branch $end
$var wire 1 $ Zero $end
$var wire 64 5 branch_target [63:0] $end
$var wire 64 6 pc_plus4 [63:0] $end
$var reg 64 7 next_pc [63:0] $end
$upscope $end
$scope module program_counter $end
$var wire 1 % clk $end
$var wire 64 8 pc_in [63:0] $end
$var wire 1 ' reset $end
$var reg 64 9 pc_out [63:0] $end
$upscope $end
$upscope $end
$upscope $end
$enddefinitions $end
$comment Show the parameter values. $end
$dumpall
$end
#0
$dumpvars
b0 9
b100 8
b100 7
b100 6
b0 5
b0 4
b10100000000000100010011 3
b0 2
b0 1
b0 0
b0 /
b100 .
b0 -
b10100000000000100010011 ,
b100 +
b0 *
b100 )
b0 (
1'
b0 &
0%
0$
0#
b10100000000000100010011 "
b0 !
$end
#5000
1%
#10000
0%
#15000
b1000 +
b1000 7
b1000 8
b101000000000000110010011 "
b101000000000000110010011 ,
b101000000000000110010011 3
b100 -
b100 2
b100 5
b1000 )
b1000 .
b1000 6
b100 !
b100 *
b100 /
b100 1
b100 4
b100 9
1%
0'
#20000
0%
#25000
b1100 +
b1100 7
b1100 8
b1100010000000010110011 "
b1100010000000010110011 ,
b1100010000000010110011 3
b1000 -
b1000 2
b1000 5
b1100 )
b1100 .
b1100 6
b1000 !
b1000 *
b1000 /
b1000 1
b1000 4
b1000 9
1%
#30000
0%
#35000
b1000000001100010000000100110011 "
b1000000001100010000000100110011 ,
b1000000001100010000000100110011 3
b10000 )
b10000 .
b10000 6
b1100 !
b1100 *
b1100 /
b1100 1
b1100 4
b1100 9
b11100 +
b11100 7
b11100 8
1$
1#
b11100 -
b11100 2
b11100 5
b10000 &
b10000 (
b10000 0
1%
#40000
0%
#45000
b101100 +
b101100 7
b101100 8
b1100010110001110110011 "
b1100010110001110110011 ,
b1100010110001110110011 3
b101100 -
b101100 2
b101100 5
b100000 )
b100000 .
b100000 6
b11100 !
b11100 *
b11100 /
b11100 1
b11100 4
b11100 9
1%
#46000
b100000 +
b100000 7
b100000 8
0$
#50000
0%
#55000
b100100 +
b100100 7
b100100 8
b100101011000000100011 "
b100101011000000100011 ,
b100101011000000100011 3
b110000 -
b110000 2
b110000 5
b100100 )
b100100 .
b100100 6
b100000 !
b100000 *
b100000 /
b100000 1
b100000 4
b100000 9
1%
#60000
0%
#65000
b101000 +
b101000 7
b101000 8
b101011010100000011 "
b101011010100000011 ,
b101011010100000011 3
b110100 -
b110100 2
b110100 5
b101000 )
b101000 .
b101000 6
b100100 !
b100100 *
b100100 /
b100100 1
b100100 4
b100100 9
1%
#70000
0%
#75000
b101100 +
b101100 7
b101100 8
b11000101011000110100011 "
b11000101011000110100011 ,
b11000101011000110100011 3
b111000 -
b111000 2
b111000 5
b101100 )
b101100 .
b101100 6
b101000 !
b101000 *
b101000 /
b101000 1
b101000 4
b101000 9
1%
