sequential/pc.v
module PC(
    input clk,
    input reset,
    input [63:0] pc_in,
    output reg [63:0] pc_out
);
    always @(posedge clk or posedge reset) begin
        if(reset)
            pc_out <= 64'd0; 
        else
            pc_out <= pc_in; 
    end
endmodule

module PC_adder(
    input [63:0] pc,
    output [63:0] pc_4
);
    assign pc_4 = pc + 64'd4; 
endmodule

module PC_branchadder(
    input [63:0] pc_curr,
    input [63:0] imm,
    output [63:0] branch_target
);
    assign branch_target = pc_curr + imm; 
endmodule

module next_pc_mux(
    input Branch,
    input Zero,
    input [63:0] pc_plus4,
    input [63:0] branch_target,
    output reg [63:0] next_pc
);
    always @(*) begin
       
        if (Branch && Zero)
            next_pc = branch_target;
        else
            next_pc = pc_plus4;
    end
endmodule

sequential/pc_tb.v
`timescale 1ns/1ps

module pc_tb;

reg clk;
reg reset;
reg Branch;
reg Zero;
reg [63:0] imm;

wire [63:0] pc_out;
wire [63:0] pc_plus4;
wire [63:0] branch_target;
wire [63:0] next_pc;

// ---------- Instantiate Modules ----------

PC pc_inst(
    .clk(clk),
    .reset(reset),
    .pc_in(next_pc),
    .pc_out(pc_out)
);

PC_adder adder_inst(
    .pc(pc_out),
    .pc_4(pc_plus4)
);

PC_branchadder branchadder_inst(
    .pc_curr(pc_out),
    .imm(imm),
    .branch_target(branch_target)
);

next_pc_mux mux_inst(
    .Branch(Branch),
    .Zero(Zero),
    .pc_plus4(pc_plus4),
    .branch_target(branch_target),
    .next_pc(next_pc)
);

// ---------- Clock ----------
always #5 clk = ~clk;   // 10ns period

// ---------- Stimulus ----------
initial begin

    $dumpfile("pc.vcd");
    $dumpvars(0, pc_tb);

    clk = 0;
    reset = 1;
    Branch = 0;
    Zero = 0;
    imm = 64'd16;

    #10 reset = 0;      // release reset

    // Normal increment
    #20;

    // Branch NOT taken
    Branch = 1;
    Zero = 0;
    #20;

    // Branch taken
    Branch = 1;
    Zero = 1;
    #20;

    // Back to normal
    Branch = 0;
    Zero = 0;
    #20;

    $finish;
end

endmodule

sequential/pc.vcd
$date
	Sun Feb 22 18:44:10 2026
$end
$version
	Icarus Verilog
$end
$timescale
	1ps
$end
$scope module pc_tb $end
$var wire 64 ! pc_plus4 [63:0] $end
$var wire 64 " pc_out [63:0] $end
$var wire 64 # next_pc [63:0] $end
$var wire 64 $ branch_target [63:0] $end
$var reg 1 % Branch $end
$var reg 1 & Zero $end
$var reg 1 ' clk $end
$var reg 64 ( imm [63:0] $end
$var reg 1 ) reset $end
$scope module adder_inst $end
$var wire 64 * pc_4 [63:0] $end
$var wire 64 + pc [63:0] $end
$upscope $end
$scope module branchadder_inst $end
$var wire 64 , imm [63:0] $end
$var wire 64 - pc_curr [63:0] $end
$var wire 64 . branch_target [63:0] $end
$upscope $end
$scope module mux_inst $end
$var wire 1 % Branch $end
$var wire 1 & Zero $end
$var wire 64 / branch_target [63:0] $end
$var wire 64 0 pc_plus4 [63:0] $end
$var reg 64 1 next_pc [63:0] $end
$upscope $end
$scope module pc_inst $end
$var wire 1 ' clk $end
$var wire 64 2 pc_in [63:0] $end
$var wire 1 ) reset $end
$var reg 64 3 pc_out [63:0] $end
$upscope $end
$upscope $end
$enddefinitions $end
$comment Show the parameter values. $end
$dumpall
$end
#0
$dumpvars
b0 3
b100 2
b100 1
b100 0
b10000 /
b10000 .
b0 -
b10000 ,
b0 +
b100 *
1)
b10000 (
0'
0&
0%
b10000 $
b100 #
b0 "
b100 !
$end
#5000
1'
#10000
0'
0)
#15000
b1000 #
b1000 1
b1000 2
b10100 $
b10100 .
b10100 /
b1000 !
b1000 *
b1000 0
b100 "
b100 +
b100 -
b100 3
1'
#20000
0'
#25000
b1100 #
b1100 1
b1100 2
b11000 $
b11000 .
b11000 /
b1100 !
b1100 *
b1100 0
b1000 "
b1000 +
b1000 -
b1000 3
1'
#30000
0'
1%
#35000
b10000 #
b10000 1
b10000 2
b11100 $
b11100 .
b11100 /
b10000 !
b10000 *
b10000 0
b1100 "
b1100 +
b1100 -
b1100 3
1'
#40000
0'
#45000
b10100 #
b10100 1
b10100 2
b100000 $
b100000 .
b100000 /
b10100 !
b10100 *
b10100 0
b10000 "
b10000 +
b10000 -
b10000 3
1'
#50000
b100000 #
b100000 1
b100000 2
0'
1&
#55000
b110000 #
b110000 1
b110000 2
b110000 $
b110000 .
b110000 /
b100100 !
b100100 *
b100100 0
b100000 "
b100000 +
b100000 -
b100000 3
1'
#60000
0'
#65000
b1000000 #
b1000000 1
b1000000 2
b1000000 $
b1000000 .
b1000000 /
b110100 !
b110100 *
b110100 0
b110000 "
b110000 +
b110000 -
b110000 3
1'
#70000
b110100 #
b110100 1
b110100 2
0'
0&
0%
#75000
b111000 #
b111000 1
b111000 2
b1000100 $
b1000100 .
b1000100 /
b111000 !
b111000 *
b111000 0
b110100 "
b110100 +
b110100 -
b110100 3
1'
#80000
0'
#85000
b111100 #
b111100 1
b111100 2
b1001000 $
b1001000 .
b1001000 /
b111100 !
b111100 *
b111100 0
b111000 "
b111000 +
b111000 -
b111000 3
1'
